AUTHORS
LICENSE
MANIFEST.in
README.md
requirements.txt
setup.cfg
setup.py
doc/man/salt-eventsd.1
doc/man/salt-eventsd.5
doc/share/doc/README
doc/share/doc/backends.txt
doc/share/doc/eventsd
doc/share/doc/eventsd.batch
doc/share/doc/eventsd.extended
doc/share/doc/mysql-example.sql
doc/share/doc/eventsd_workers/Bench_Worker.py
doc/share/doc/eventsd_workers/Elasticsearch_Worker.py
doc/share/doc/eventsd_workers/Minion_Batch_Return_Worker.py
doc/share/doc/eventsd_workers/Minion_Return_Worker.py
doc/share/doc/eventsd_workers/Minion_Sub_Worker.py
doc/share/doc/eventsd_workers/New_Job_Worker.py
doc/share/doc/eventsd_workers/Stat_Worker.py
salt_eventsd.egg-info/PKG-INFO
salt_eventsd.egg-info/SOURCES.txt
salt_eventsd.egg-info/dependency_links.txt
salt_eventsd.egg-info/requires.txt
salt_eventsd.egg-info/top_level.txt
salteventsd/__init__.py
salteventsd/backends.py
salteventsd/daemon.py
salteventsd/loader.py
salteventsd/mysql.py
salteventsd/timer.py
salteventsd/worker.py
scripts/salt-eventsd