Metadata-Version: 1.1
Name: salt-eventsd
Version: 0.9.3
Summary: Daemon that collects events from the salt-event-bus and writes them into any backend, mysql, redis, etc.
Home-page: https://github.com/felskrone/salt-eventsd
Author: Volker Schwicking
Author-email: vs@hosteurope.de
License: UNKNOWN
Keywords: saltstack,salt
Platform: UNKNOWN
Classifier: Programming Language :: Python
Classifier: Programming Language :: Python :: 2.6
Classifier: Programming Language :: Python :: 2.7
Classifier: Development Status :: 5 - Production/Stable
Classifier: Environment :: Console
Classifier: Intended Audience :: Developers
Classifier: Intended Audience :: Information Technology
Classifier: Intended Audience :: System Administrators
Classifier: License :: OSI Approved :: Apache Software License
Classifier: Operating System :: POSIX :: Linux
Classifier: Topic :: System :: Distributed Computing
